.gitignore
CHANGES.txt
LICENSE.txt
MANIFEST.in
README.txt
bootstrap.py
buildout.cfg
package.json
setup.py
js/__init__.py
js.fullcalendar.egg-info/PKG-INFO
js.fullcalendar.egg-info/SOURCES.txt
js.fullcalendar.egg-info/dependency_links.txt
js.fullcalendar.egg-info/entry_points.txt
js.fullcalendar.egg-info/namespace_packages.txt
js.fullcalendar.egg-info/not-zip-safe
js.fullcalendar.egg-info/requires.txt
js.fullcalendar.egg-info/top_level.txt
js/fullcalendar/__init__.py
js/fullcalendar/test_fullcalendar.txt
js/fullcalendar/resources/fullcalendar.css
js/fullcalendar/resources/fullcalendar.js
js/fullcalendar/resources/fullcalendar.min.css
js/fullcalendar/resources/fullcalendar.min.js
js/fullcalendar/resources/fullcalendar.print.css
js/fullcalendar/resources/gcal.js
js/fullcalendar/resources/lang-all.js
js/fullcalendar/resources/lang/ar-ma.js
js/fullcalendar/resources/lang/ar-sa.js
js/fullcalendar/resources/lang/ar-tn.js
js/fullcalendar/resources/lang/ar.js
js/fullcalendar/resources/lang/bg.js
js/fullcalendar/resources/lang/ca.js
js/fullcalendar/resources/lang/cs.js
js/fullcalendar/resources/lang/da.js
js/fullcalendar/resources/lang/de-at.js
js/fullcalendar/resources/lang/de.js
js/fullcalendar/resources/lang/el.js
js/fullcalendar/resources/lang/en-au.js
js/fullcalendar/resources/lang/en-ca.js
js/fullcalendar/resources/lang/en-gb.js
js/fullcalendar/resources/lang/en-ie.js
js/fullcalendar/resources/lang/en-nz.js
js/fullcalendar/resources/lang/es.js
js/fullcalendar/resources/lang/eu.js
js/fullcalendar/resources/lang/fa.js
js/fullcalendar/resources/lang/fi.js
js/fullcalendar/resources/lang/fr-ca.js
js/fullcalendar/resources/lang/fr-ch.js
js/fullcalendar/resources/lang/fr.js
js/fullcalendar/resources/lang/gl.js
js/fullcalendar/resources/lang/he.js
js/fullcalendar/resources/lang/hi.js
js/fullcalendar/resources/lang/hr.js
js/fullcalendar/resources/lang/hu.js
js/fullcalendar/resources/lang/id.js
js/fullcalendar/resources/lang/is.js
js/fullcalendar/resources/lang/it.js
js/fullcalendar/resources/lang/ja.js
js/fullcalendar/resources/lang/ko.js
js/fullcalendar/resources/lang/lb.js
js/fullcalendar/resources/lang/lt.js
js/fullcalendar/resources/lang/lv.js
js/fullcalendar/resources/lang/nb.js
js/fullcalendar/resources/lang/nl.js
js/fullcalendar/resources/lang/nn.js
js/fullcalendar/resources/lang/pl.js
