Metadata-Version: 1.0
Name: js.fullcalendar
Version: 2.9.1
Summary: Fanstatic packaging of FullCalendar
Home-page: https://github.com/Kotti/js.fullcalendar
Author: Andreas Kaiser
Author-email: disko@binary-punks.com
License: BSD
Platform: UNKNOWN
